TextProcessing/CustomException.py
TextProcessing/DataAndProcessing.py
TextProcessing/TopicModelling.py
TextProcessing/__init__.py
TextPreProc-1.7.dist-info/LICENSE
TextPreProc-1.7.dist-info/METADATA
TextPreProc-1.7.dist-info/WHEEL
TextPreProc-1.7.dist-info/top_level.txt
TextPreProc-1.7.dist-info/RECORD
